README.txt
setup.py
ssher/__init__.py
ssher/ssher.py
ssher2.egg-info/PKG-INFO
ssher2.egg-info/SOURCES.txt
ssher2.egg-info/dependency_links.txt
ssher2.egg-info/requires.txt
ssher2.egg-info/top_level.txt
ssher2.egg-info/zip-safe